hnte_codec/__init__.py
hnte_codec/codec.py
hnte_codec-2.0.0.dist-info/licenses/LICENSE
hnte_codec-2.0.0.dist-info/METADATA
hnte_codec-2.0.0.dist-info/WHEEL
hnte_codec-2.0.0.dist-info/top_level.txt
hnte_codec-2.0.0.dist-info/RECORD
