Metadata-Version: 2.4
Name: hnte-codec
Version: 2.0.0
Summary: HNTE compressed & encrypted file format codec, takes less space than usual text files.(花のテクストエクステンション　－ Hana no Text Extension)
Author-email: Elif İrem Atmaca <elifirematmaca2010@gmail.com>
License: MIT
Project-URL: Homepage, https://github.com/ElifIremAtmaca/hnte-codec
Project-URL: Source, https://github.com/ElifIremAtmaca/hnte_codec
Project-URL: Issues, https://github.com/ElifIremAtmaca/hnte_codec/issues
Requires-Python: >=3.8
License-File: LICENSE
Requires-Dist: cryptography>=42.0.0
Dynamic: license-file
